dz_sqloxide-0.1.26.dist-info/RECORD
dz_sqloxide-0.1.26.dist-info/METADATA
dz_sqloxide-0.1.26.dist-info/top_level.txt
dz_sqloxide-0.1.26.dist-info/LICENSE
dz_sqloxide-0.1.26.dist-info/WHEEL
sqloxide/__init__.py
sqloxide/sqloxide.cpython-39-i386-linux-gnu.so
